LICENSE.TXT
MANIFEST.in
NOTICE.TXT
README.rst
setup.py
Monary.egg-info/PKG-INFO
Monary.egg-info/SOURCES.txt
Monary.egg-info/dependency_links.txt
Monary.egg-info/requires.txt
Monary.egg-info/top_level.txt
monary/__init__.py
monary/cmonary.c
monary/datehelper.py
monary/monary.py
monary/monary_param.py
monary/ordereddict.py
monary/write_concern.py