Metadata-Version: 1.1
Name: Monary
Version: 0.5.0
Summary: Monary performs high-performance column queries on MongoDB
Home-page: http://bitbucket.org/djcbeach/monary/
Author: David J. C. Beach
Author-email: info@djcinnovations.com
License: UNKNOWN
Keywords: monary pymongo mongo mongodb numpy array
Platform: UNKNOWN
Classifier: Development Status :: 4 - Beta
Classifier: Intended Audience :: Science/Research
Classifier: License :: OSI Approved :: Apache Software License
Classifier: Operating System :: Unix
Classifier: Operating System :: Microsoft :: Windows
Classifier: Environment :: Console
Classifier: Programming Language :: Python
Classifier: Programming Language :: Python :: 2.6
Classifier: Programming Language :: Python :: 2.7
Classifier: Programming Language :: Python :: 3.3
Classifier: Programming Language :: Python :: 3.4
Classifier: Programming Language :: Python :: Implementation :: CPython
Classifier: Topic :: Database
